user_app/__init__.py
user_app/admin.py
user_app/apps.py
user_app/context_processors.py
user_app/forms.py
user_app/models.py
user_app/tests.py
user_app/urls.py
user_app/views.py
user_app/migrations/0001_initial.py
user_app/migrations/__init__.py
user_app/templates/base.html
user_app/templates/navbar.html
user_app/templates/registration/logged_out.html
user_app/templates/registration/login.html
user_app/templates/registration/password_reset_complete.html
user_app/templates/registration/password_reset_confirm.html
user_app/templates/registration/password_reset_done.html
user_app/templates/registration/password_reset_form.html
user_app/templates/user_app/nav.html
user_app/templates/user_app/register.html
user_app/templates/user_app/settings/connections.html
user_app/templates/user_app/settings/password.html
user_app/templates/user_app/settings/profile.html
user_app/templates/user_app/settings/user.html
django_user_app-0.0.6.dist-info/LICENSE
django_user_app-0.0.6.dist-info/METADATA
django_user_app-0.0.6.dist-info/WHEEL
django_user_app-0.0.6.dist-info/top_level.txt
django_user_app-0.0.6.dist-info/RECORD
