Metadata-Version: 2.1
Name: django-user-app
Version: 0.0.6
Summary: A user app for Django3
Home-page: https://github.com/Couapy/django-user-app
Author: Couapy
Author-email: contact@marchand.cloud
License: MIT
Platform: UNKNOWN
Classifier: Programming Language :: Python :: 3
Classifier: License :: OSI Approved :: MIT License
Classifier: Operating System :: OS Independent
Requires-Python: >=3.6
Requires-Dist: Django (==3.0.8)
Requires-Dist: Pillow (==7.2.0)
Requires-Dist: social-auth-app-django (==4.0.0)
Requires-Dist: django-crispy-forms (==1.9.2)
